bsonsearch/__init__.py
bsonsearch/matcher_module.cpython-313-aarch64-linux-musl.so
bsonsearch/matcher_ext/matcher_module.c
bsonsearch.libs/libbson2-b3aafaa9.so.2.1.2
bsonsearch.libs/libbsonsearch-47ac8cc6.so
bsonsearch.libs/libcmph-48f5390e.so.0.0.0
bsonsearch.libs/libdiscodb-b1f31358.so
bsonsearch.libs/libduktape-2de225b8.so.207.20700
bsonsearch.libs/libpcre-9b87d85d.so.1.2.13
bsonsearch-2.1.2.dist-info/METADATA
bsonsearch-2.1.2.dist-info/WHEEL
bsonsearch-2.1.2.dist-info/top_level.txt
bsonsearch-2.1.2.dist-info/RECORD
bsonsearch-2.1.2.dist-info/licenses/LICENSE
