Metadata-Version: 2.4
Name: bsonsearch
Version: 2.1.2
Summary: compare BSON/JSON documents locally
Author: Dan Bauman
Maintainer: Dan Bauman
Requires-Python: >=3.11
License-File: LICENSE
Dynamic: license-file
